{
  "stages": [
    {
      "id": 1,
      "name": "Stage 1: 워밍업",
      "pairs": 2,
      "categories": ["numbers"],
      "lives": 3,
      "hints": 0,
      "previewDuration": 4.0
    },
    {
      "id": 2,
      "name": "Stage 2: 쉬운 시작",
      "pairs": 2,
      "categories": ["numbers", "dice"],
      "lives": 3,
      "hints": 0,
      "previewDuration": 4.0
    },
    {
      "id": 3,
      "name": "Stage 3: 조금 더",
      "pairs": 2,
      "categories": ["numbers", "dice"],
      "lives": 3,
      "hints": 0,
      "previewDuration": 4.0
    },
    {
      "id": 4,
      "name": "Stage 4: 속도 향상",
      "pairs": 3,
      "categories": ["numbers", "dice"],
      "lives": 3,
      "hints": 0,
      "previewDuration": 4.0
    },
    {
      "id": 5,
      "name": "Stage 5: 도전 시작",
      "pairs": 3,
      "categories": ["numbers", "dice"],
      "lives": 3,
      "hints": 0,
      "previewDuration": 4.0
    },
    {
      "id": 6,
      "name": "Stage 6: 집중력 테스트",
      "pairs": 3,
      "categories": ["numbers", "dice"],
      "lives": 4,
      "hints": 1,
      "previewDuration": 4.0
    },
    {
      "id": 7,
      "name": "Stage 7: 중급 레벨",
      "pairs": 4,
      "categories": ["numbers", "dice"],
      "lives": 4,
      "hints": 1,
      "previewDuration": 4.0
    },
    {
      "id": 8,
      "name": "Stage 8: 빠른 기억",
      "pairs": 4,
      "categories": ["numbers", "dice"],
      "lives": 4,
      "hints": 1,
      "previewDuration": 4.0
    },
    {
      "id": 9,
      "name": "Stage 9: 최대 카드",
      "pairs": 4,
      "categories": ["numbers", "dice"],
      "lives": 4,
      "hints": 1,
      "previewDuration": 4.0
    },
    {
      "id": 10,
      "name": "Stage 10: 반환점",
      "pairs": 5,
      "categories": ["numbers", "dice"],
      "lives": 4,
      "hints": 1,
      "previewDuration": 4.0
    },
    {
      "id": 11,
      "name": "Stage 11: 상급 도전",
      "pairs": 5,
      "categories": ["numbers", "dice"],
      "lives": 4,
      "hints": 2,
      "previewDuration": 3.0
    },
    {
      "id": 12,
      "name": "Stage 12: 순간 기억",
      "pairs": 5,
      "categories": ["numbers", "dice"],
      "lives": 4,
      "hints": 2,
      "previewDuration": 3.0
    },
    {
      "id": 13,
      "name": "Stage 13: 고난의 시작",
      "pairs": 5,
      "categories": ["numbers", "dice"],
      "lives": 4,
      "hints": 2,
      "previewDuration": 3.0
    },
    {
      "id": 14,
      "name": "Stage 14: 극한 집중",
      "pairs": 6,
      "categories": ["numbers", "dice"],
      "lives": 4,
      "hints": 2,
      "previewDuration": 3.0
    },
    {
      "id": 15,
      "name": "Stage 15: 마스터 도전",
      "pairs": 6,
      "categories": ["numbers", "dice"],
      "lives": 4,
      "hints": 2,
      "previewDuration": 3.0
    },
    {
      "id": 16,
      "name": "Stage 16: 전문가 레벨",
      "pairs": 6,
      "categories": ["numbers", "dice"],
      "lives": 5,
      "hints": 2,
      "previewDuration": 2.0
    },
    {
      "id": 17,
      "name": "Stage 17: 거의 불가능",
      "pairs": 7,
      "categories": ["numbers", "dice"],
      "lives": 5,
      "hints": 3,
      "previewDuration": 2.0
    },
    {
      "id": 18,
      "name": "Stage 18: 천재의 영역",
      "pairs": 7,
      "categories": ["numbers", "dice"],
      "lives": 5,
      "hints": 2,
      "previewDuration": 2.0
    },
    {
      "id": 19,
      "name": "Stage 19: 최종 관문",
      "pairs": 7,
      "categories": ["numbers", "dice"],
      "lives": 5,
      "hints": 2,
      "previewDuration": 2.0
    },
    {
      "id": 20,
      "name": "Stage 20: 전설의 챔피언",
      "pairs": 8,
      "categories": ["numbers", "dice"],
      "lives": 5,
      "hints": 3,
      "previewDuration": 2.0
    },
    {
      "id": 21,
      "name": "Stage 21: 새로운 도전",
      "pairs": 8,
      "categories": ["numbers", "dice"],
      "lives": 5,
      "hints": 3,
      "previewDuration": 1.0
    },
    {
      "id": 22,
      "name": "Stage 22: 기억력 마스터",
      "pairs": 8,
      "categories": ["numbers", "dice"],
      "lives": 5,
      "hints": 3,
      "previewDuration": 1.0
    },
    {
      "id": 23,
      "name": "Stage 23: 집중력 극한",
      "pairs": 9,
      "categories": ["numbers", "dice"],
      "lives": 5,
      "hints": 3,
      "previewDuration": 1.0
    },
    {
      "id": 24,
      "name": "Stage 24: 기억의 달인",
      "pairs": 9,
      "categories": ["numbers", "dice"],
      "lives": 5,
      "hints": 3,
      "previewDuration": 1.0
    },
    {
      "id": 25,
      "name": "Stage 25: 완벽한 기억",
      "pairs": 9,
      "categories": ["numbers", "dice"],
      "lives": 5,
      "hints": 3,
      "previewDuration": 1.0
    },
    {
      "id": 26,
      "name": "Stage 26: 초인적 집중",
      "pairs": 9,
      "categories": ["numbers", "dice"],
      "lives": 5,
      "hints": 3,
      "previewDuration": 1.0
    },
    {
      "id": 27,
      "name": "Stage 27: 기억의 신",
      "pairs": 9,
      "categories": ["numbers", "dice"],
      "lives": 5,
      "hints": 3,
      "previewDuration": 1.0
    },
    {
      "id": 28,
      "name": "Stage 28: 불가능한 도전",
      "pairs": 9,
      "categories": ["numbers", "dice"],
      "lives": 5,
      "hints": 3,
      "previewDuration": 1.0
    },
    {
      "id": 29,
      "name": "Stage 29: 최후의 시험",
      "pairs": 9,
      "categories": ["numbers", "dice"],
      "lives": 5,
      "hints": 3,
      "previewDuration": 1.0
    },
    {
      "id": 30,
      "name": "Stage 30: 궁극의 챔피언",
      "pairs": 9,
      "categories": ["numbers", "dice"],
      "lives": 5,
      "hints": 3,
      "previewDuration": 1.0
    }
  ]
}
